octostorelib/__init__.py
octostorelib/main.py
octostorelib-0.0.6.dist-info/LICENSE
octostorelib-0.0.6.dist-info/METADATA
octostorelib-0.0.6.dist-info/WHEEL
octostorelib-0.0.6.dist-info/top_level.txt
octostorelib-0.0.6.dist-info/RECORD
