Metadata-Version: 2.1
Name: octostorelib
Version: 0.0.6
Summary: Library to simplify writing out events during CI/CD workflows.
Home-page: https://github.com/octostore/octostorelib
Author: David Aronchick
Author-email: aronchick@gmail.com
License: MIT License
Keywords: Octostore
Platform: UNKNOWN
Classifier: Development Status :: 3 - Alpha
Classifier: Intended Audience :: Developers
Classifier: Topic :: Software Development :: Build Tools
Classifier: License :: OSI Approved :: MIT License
Classifier: Programming Language :: Python :: 3
Classifier: Programming Language :: Python :: 3.4
Classifier: Programming Language :: Python :: 3.5
Classifier: Programming Language :: Python :: 3.6
Classifier: Programming Language :: Python :: 3.7
Classifier: Programming Language :: Python :: 3.8
Requires-Dist: ipython
Requires-Dist: msgpack
Requires-Dist: opentelemetry-api
Requires-Dist: opentelemetry-sdk
Requires-Dist: environs
Requires-Dist: setuptools
Requires-Dist: attrdict
Requires-Dist: python-dotenv
